atombench/__init__.py
atombench-2022.7.15.dist-info/LICENSE
atombench-2022.7.15.dist-info/METADATA
atombench-2022.7.15.dist-info/WHEEL
atombench-2022.7.15.dist-info/top_level.txt
atombench-2022.7.15.dist-info/RECORD
